setup.cfg
setup.py
goldencheetahlib/__init__.py
goldencheetahlib/client.py
goldencheetahlib/constants.py
goldencheetahlib/exceptions.py
goldencheetahlib.egg-info/PKG-INFO
goldencheetahlib.egg-info/SOURCES.txt
goldencheetahlib.egg-info/dependency_links.txt
goldencheetahlib.egg-info/top_level.txt
tests/__init__.py
tests/test_client.py
tests/vcr_config.py