Metadata-Version: 1.1
Name: goldencheetahlib
Version: 0.8.0
Summary: Python library that provides access to the GoldenCheeetah REST API
Home-page: https://github.com/AartGoossens/goldencheetahlib
Author: Aart Goossens
Author-email: aart@goossens.me
License: UNKNOWN
Download-URL: https://github.com/AartGoossens/goldencheetahlib/tarball/0.4.0
Keywords: workout,goldencheetah,cycling
Platform: UNKNOWN
